ipf/__init__.py
ipf/_version.py
ipf/assert_py_ver.py
ipf/build_helper.py
ipf/catalog.py
ipf/daemon.py
ipf/data.py
ipf/dt.py
ipf/engine.py
ipf/error.py
ipf/fileread.py
ipf/ipfinfo.py
ipf/log.py
ipf/paths.py
ipf/pre_populate_position.py
ipf/publish.py
ipf/run_workflow.py
ipf/step.py
ipf/step_info.py
ipf/sysinfo.py
ipf/urnprefix.py
ipf/workflow.py
ipf/bin/configure_extmodules
ipf/bin/create_cacerts.sh
ipf/bin/run_workflow
ipf/bin/save_configs.sh
ipf/bin/wfm
ipf/configure/__init__.py
ipf/configure/configure_workflows.py
ipf/configure/sysinfo.py
ipf/configure/test/README.rst
ipf/configure/test/subscribe_amqp.py
ipf/configure/test/validate.py
ipf/configure/test/validate_activities.py
ipf/configure/test/validate_compute.py
ipf/configure/test/validate_modules.py
ipf/etc/amqp.conf.sample
ipf/etc/cleanse.conf
ipf/etc/configure_extmodules.conf.sample
ipf/etc/requirements.txt
ipf/etc/shell.conf
ipf/etc/ipf/ctss_glue2_envelope.xsd
ipf/etc/ipf/logging.conf
ipf/etc/ipf/teragrid_glue_2.0_r02.xsd
ipf/etc/ipf/ca-certificates/README.md
ipf/etc/ipf/ca-certificates/ca_certs.pem
ipf/etc/ipf/ca-certificates/incommon_igtf_ca3.pem
ipf/etc/ipf/ca-certificates/incommon_rsa_ca2.pem
ipf/etc/ipf/ca-certificates/isrg-root-x1.pem
ipf/etc/ipf/ca-certificates/isrg-root-x2.pem
ipf/etc/ipf/ca-certificates/mk_ca_certs.sh
ipf/etc/ipf/init.d/ipf-WORKFLOW
ipf/etc/ipf/workflow/ipfinfo.json
ipf/etc/ipf/workflow/ipfinfo_publish_periodic.json
ipf/etc/ipf/workflow/sysinfo.json
ipf/etc/ipf/workflow/sysinfo_publish.json
ipf/etc/ipf/workflow/sysinfo_publish_periodic.json
ipf/etc/ipf/workflow/glue2/empty.txt
ipf/etc/ipf/workflow/templates/generic_print.json
ipf/etc/ipf/workflow/templates/generic_publish.json
ipf/etc/ipf/workflow/templates/glue2/abstractservice.json
ipf/etc/ipf/workflow/templates/glue2/catalina_pbs_compute.json
ipf/etc/ipf/workflow/templates/glue2/condor_compute.json
ipf/etc/ipf/workflow/templates/glue2/extmodules.json
ipf/etc/ipf/workflow/templates/glue2/extmodulesremote.json
ipf-1.9.4.dist-info/licenses/LICENSE
ipf-1.9.4.dist-info/METADATA
ipf-1.9.4.dist-info/WHEEL
ipf-1.9.4.dist-info/top_level.txt
ipf-1.9.4.dist-info/RECORD
