Metadata-Version: 2.4
Name: ipf
Version: 1.9.4
Summary: ACCESS Information Publishing Framework
Author: Warren Smith
Author-email: Eric Blau <blau@globus.org>
Project-URL: Repository, https://github.com/access-ci-org/ipf
Keywords: monitoring,information,gathering,publishing,glue2
Classifier: Development Status :: 5 - Production/Stable
Classifier: Programming Language :: Python :: 3
Classifier: Topic :: System :: Monitoring
Requires-Python: >=3.6
License-File: LICENSE
Requires-Dist: amqp>=1.4
Requires-Dist: lupa
Requires-Dist: python-dateutil
Dynamic: license-file
